LICENSE
README.md
setup.cfg
setup.py
unstable_baselines/__init__.py
unstable_baselines.egg-info/PKG-INFO
unstable_baselines.egg-info/SOURCES.txt
unstable_baselines.egg-info/dependency_links.txt
unstable_baselines.egg-info/requires.txt
unstable_baselines.egg-info/top_level.txt
unstable_baselines/algo/__init__.py
unstable_baselines/algo/d/__init__.py
unstable_baselines/algo/dqn/__init__.py
unstable_baselines/algo/dqn/model.py
unstable_baselines/algo/ppo/__init__.py
unstable_baselines/algo/ppo/model.py
unstable_baselines/algo/s/__init__.py
unstable_baselines/lib/__init__.py
unstable_baselines/lib/base.py
unstable_baselines/lib/data.py
unstable_baselines/lib/nets.py
unstable_baselines/lib/patch.py
unstable_baselines/lib/prob.py
unstable_baselines/lib/sche.py
unstable_baselines/lib/utils.py
unstable_baselines/lib/envs/__init__.py
unstable_baselines/lib/envs/monitor.py
unstable_baselines/lib/envs/vec/__init__.py
unstable_baselines/lib/envs/vec/base.py
unstable_baselines/lib/envs/vec/dummy.py
unstable_baselines/lib/envs/vec/subproc.py
unstable_baselines/lib/envs/wrap/__init__.py
unstable_baselines/lib/envs/wrap/atari.py
unstable_baselines/lib/envs/wrap/common.py
unstable_baselines/logger/__init__.py
unstable_baselines/logger/cmd_colors.py
unstable_baselines/logger/formatter.py
unstable_baselines/logger/logger.py
unstable_baselines/logger/test.py
unstable_baselines/logger/ascii_font/__init__.py
unstable_baselines/logger/ascii_font/base.py
unstable_baselines/logger/ascii_font/compile.py
unstable_baselines/logger/ascii_font/pkl/ANSI_Shadow.pkl
unstable_baselines/logger/ascii_font/pkl/Big.pkl
unstable_baselines/logger/ascii_font/pkl/Bubble.pkl
unstable_baselines/logger/ascii_font/pkl/Buldhead.pkl
unstable_baselines/logger/ascii_font/pkl/Cards.pkl
unstable_baselines/logger/ascii_font/pkl/Dancing_Font.pkl
unstable_baselines/logger/ascii_font/pkl/Doom.pkl
unstable_baselines/logger/ascii_font/pkl/Elite.pkl
unstable_baselines/logger/ascii_font/pkl/Gothic.pkl
unstable_baselines/logger/ascii_font/pkl/Graceful.pkl
unstable_baselines/logger/ascii_font/pkl/Invita.pkl
unstable_baselines/logger/ascii_font/pkl/JS_Bracket_Letters.pkl
unstable_baselines/logger/ascii_font/pkl/Ogre.pkl
