Metadata-Version: 2.1
Name: unstable-baselines
Version: 0.1.0a0
Summary: A TensorFlow 2.0 implemented RL baselines
Home-page: https://github.com/Ending2015a/unstable_baselines
Author: JoeHsiao
Author-email: joehsiao@gapp.nthu.edu.tw
License: MIT
Keywords: reinforcement-learning playform tensorflow-2.0 tensorflow
Platform: UNKNOWN
Classifier: Development Status :: 2 - Pre-Alpha
Classifier: Intended Audience :: Science/Research
Classifier: Topic :: Scientific/Engineering :: Artificial Intelligence
Classifier: Topic :: Software Development :: Libraries :: Python Modules
Classifier: License :: OSI Approved :: MIT License
Classifier: Programming Language :: Python :: 3.6
Classifier: Programming Language :: Python :: 3.7
Classifier: Programming Language :: Python :: 3.8
Classifier: Programming Language :: Python :: 3.9
Requires-Python: >=3.6
Provides-Extra: dev
Provides-Extra: atari
Provides-Extra: pybullet
Provides-Extra: extra
License-File: LICENSE
